pyjuni/__init__.py
pyjuni/deflib.py
pyjuni/jcboard.py
pyjuni/jdcode.py
pyjuni/jdmission.py
pyjuni/jkeyevent.py
pyjuni/packet.py
pyjuni/parse.py
pyjuni/robodog.py
pyjuni/uglybot.py
pyjuni-1.7.dist-info/METADATA
pyjuni-1.7.dist-info/WHEEL
pyjuni-1.7.dist-info/top_level.txt
pyjuni-1.7.dist-info/RECORD
