Metadata-Version: 2.1
Name: pyjuni
Version: 1.7
Summary: Library for Junilab Products
Home-page: http://www.junilab.co.kr
Author: Junilab
Author-email: help@junilab.co.kr
Requires-Dist: pyserial>=3.4
Requires-Dist: pynput>=1.7.3
